lightning_hpo/__about__.py
lightning_hpo/__init__.py
lightning_hpo/setup_tools.py
lightning_hpo/algorithm/__init__.py
lightning_hpo/algorithm/base.py
lightning_hpo/algorithm/optuna.py
lightning_hpo/app/__init__.py
lightning_hpo/app/main.py
lightning_hpo/app/ui/.prettierrc
lightning_hpo/app/ui/README.md
lightning_hpo/app/ui/craco.config.js
lightning_hpo/app/ui/yarn.lock
lightning_hpo/app/ui/build/favicon.svg
lightning_hpo/app/ui/build/index.html
lightning_hpo/app/ui/build/robots.txt
lightning_hpo/app/ui/build/static/css/main.2c16595e.css
lightning_hpo/app/ui/build/static/css/main.2c16595e.css.map
lightning_hpo/app/ui/build/static/js/787.9615c779.chunk.js
lightning_hpo/app/ui/build/static/js/787.9615c779.chunk.js.map
lightning_hpo/app/ui/build/static/js/main.74acfbc3.js
lightning_hpo/app/ui/build/static/js/main.74acfbc3.js.LICENSE.txt
lightning_hpo/app/ui/build/static/js/main.74acfbc3.js.map
lightning_hpo/app/ui/build/static/media/UCity-Light.8352e423a843d9a0c52a.otf
lightning_hpo/app/ui/build/static/media/UCity-Regular.e28f5006c1976d08baaa.otf
lightning_hpo/app/ui/build/static/media/UCity-Semibold.b37489cc447430fe4ba7.otf
lightning_hpo/app/ui/build/static/media/cloud.7aee0ddfc3bf81079995a22e719e53fb.svg
lightning_hpo/app/ui/build/static/media/error.11892047d0183a4723b91dc0fb98cb95.svg
lightning_hpo/app/ui/build/static/media/success.5edae4c5b171e2c1c5a3c54273c47ba8.svg
lightning_hpo/app/ui/build/static/media/warning.5c542673e84e77ceb6a230bfea7f7263.svg
lightning_hpo/app/ui/public/favicon.svg
lightning_hpo/app/ui/public/index.html
lightning_hpo/app/ui/public/robots.txt
lightning_hpo/app/ui/src/App.tsx
lightning_hpo/app/ui/src/index.css
lightning_hpo/app/ui/src/index.tsx
lightning_hpo/app/ui/src/reportWebVitals.ts
lightning_hpo/app/ui/src/svg.d.ts
lightning_hpo/app/ui/src/utilities.ts
lightning_hpo/app/ui/src/assets/cloud.svg
lightning_hpo/app/ui/src/components/BorderLinearProgress.tsx
lightning_hpo/app/ui/src/components/DataTable.tsx
lightning_hpo-0.0.7.dist-info/LICENSE
lightning_hpo-0.0.7.dist-info/METADATA
lightning_hpo-0.0.7.dist-info/WHEEL
lightning_hpo-0.0.7.dist-info/top_level.txt
lightning_hpo-0.0.7.dist-info/RECORD
