Metadata-Version: 2.1
Name: lightning-hpo
Version: 0.0.7
Summary: Lightning HPO
Home-page: https://github.com/PyTorchLightning/lightning
Download-URL: https://github.com/Lightning-AI/lightning-hpo
Author: PyTorchLightning et al.
Author-email: thomas@grid.ai
License: TBD
Keywords: deep learning,pytorch,AI
Requires-Python: >=3.6
License-File: LICENSE
Requires-Dist: jsonargparse[signatures]
Requires-Dist: pytorch-lightning
Requires-Dist: lightning (>=1.8.4)
Requires-Dist: lightning-jupyter
Requires-Dist: torchvision
Requires-Dist: optuna
Requires-Dist: sqlmodel
Requires-Dist: wandb
Requires-Dist: streamlit
Requires-Dist: sqlalchemy
Requires-Dist: hiplot
Requires-Dist: scikit-learn
Requires-Dist: sqlite-web
Requires-Dist: hydra-core
